datalab_client-1.0.18.data/scripts/datalab
datalab_client-1.0.18.data/scripts/mountvofs
datalab_client-1.0.18.dist-info/DESCRIPTION.rst
datalab_client-1.0.18.dist-info/METADATA
datalab_client-1.0.18.dist-info/RECORD
datalab_client-1.0.18.dist-info/WHEEL
datalab_client-1.0.18.dist-info/metadata.json
datalab_client-1.0.18.dist-info/top_level.txt
dl/__init__.py
dl/__version__.py
dl/authClient.py
dl/dlinterface.py
dl/dltasks.py
dl/helpers.py
dl/queryClient.py
dl/storeClient.py
vos/BitVector.py
vos/CacheMetaData.py
vos/CadcCache.py
vos/NodeCache.py
vos/SharedLock.py
vos/__init__.py
vos/__version__.py
vos/cantop.py
vos/commonparser.py
vos/fuse.py
vos/html2text.py
vos/logExceptions.py
vos/md5_cache.py
vos/utils.py
vos/vofs.py
vos/vos.py
