Metadata-Version: 2.0
Name: datalab-client
Version: 1.0.18
Summary: Tools for interacting with NOAO Data Lab.
Home-page: https://github.noao.edu/noao-datalab/datalab-client
Author: M.J. Graham, M.J. Fitzpatrick, D.L. Nidever, R. Nikutta
Author-email: graham@noao.edu, fitz@noao.edu, dnidever@noao.edu, nikutta@noao.edu
License: UNKNOWN
Platform: UNKNOWN
Classifier: Development Status :: 4 - Beta
Classifier: Environment :: Console
Classifier: Intended Audience :: Developers
Classifier: Intended Audience :: End Users/Desktop
Classifier: Intended Audience :: Science/Research
Classifier: License :: OSI Approved :: GNU Affero General Public License v3
Classifier: Operating System :: POSIX
Classifier: Programming Language :: Python
Requires: requests (>=2.7)
Requires: argparse
Requires: lxml
Requires: httplib2
Requires: numpy
Requires: astropy
Requires: pyvo
Requires: matplotlib
Requires: html2text
Requires-Dist: argparse
Requires-Dist: astropy
Requires-Dist: html2text
Requires-Dist: httplib2
Requires-Dist: lxml
Requires-Dist: matplotlib
Requires-Dist: numpy
Requires-Dist: pyvo
Requires-Dist: requests (>=2.7)
